{
  "items": [
    {
      "name": "Ceramic Glaze Set",
      "stable_id": "inv-187",
      "location": "Arts Stockroom",
      "status": "reorder",
      "lifecycle": "current"
    },
    {
      "name": "Canvas Panel Case",
      "stable_id": "inv-587",
      "location": "Teaching Studio",
      "status": "monitor",
      "lifecycle": "current"
    },
    {
      "name": "Ceramic Glaze Set",
      "stable_id": "inv-087",
      "location": "Arts Stockroom",
      "status": "retired",
      "lifecycle": "stale"
    },
    {
      "name": "Canvas Panel Case",
      "stable_id": "inv-487",
      "location": "Teaching Studio",
      "status": "closed",
      "lifecycle": "stale"
    },
    {
      "name": "Ceramic Glaze Set",
      "stable_id": "inv-987",
      "location": "Arts Stockroom Annex",
      "status": "in-stock",
      "lifecycle": "current"
    },
    {
      "name": "Canvas Panel Case - Archive",
      "stable_id": "inv-887",
      "location": "Teaching Studio",
      "status": "retired",
      "lifecycle": "current"
    }
  ],
  "preferences": {
    "default_location": "Central Receiving",
    "saved_view": "replenishment-watch"
  },
  "availability": [
    {
      "name": "Ceramic Glaze Set",
      "location": "Arts Stockroom",
      "date": "2026-07-22",
      "available": false
    }
  ],
  "notifications": []
}
